setup.py
colored/__init__.py
colored/attributes.py
colored/background.py
colored/call.py
colored/colored.py
colored/controls.py
colored/cprint.py
colored/exceptions.py
colored/foreground.py
colored/hexadecimal.py
colored/library.py
colored/utilities.py
upgrade_colored.egg-info/PKG-INFO
upgrade_colored.egg-info/SOURCES.txt
upgrade_colored.egg-info/dependency_links.txt
upgrade_colored.egg-info/requires.txt
upgrade_colored.egg-info/top_level.txt