Metadata-Version: 2.1
Name: upgrade-colored
Version: 0.0.1
Summary: upgrade-colored
Author: upgrade-colored
